MANIFEST.in
fleet_board_view.xml
fleet_cars.xml
fleet_data.xml
fleet_demo.xml
fleet_view.xml
setup.py
./__init__.py
./__openerp__.py
./fleet.py
i18n/ar.po
i18n/bg.po
i18n/cs.po
i18n/da.po
i18n/de.po
i18n/es.po
i18n/es_MX.po
i18n/fleet.pot
i18n/fr.po
i18n/hr.po
i18n/hu.po
i18n/it.po
i18n/lo.po
i18n/lv.po
i18n/mk.po
i18n/mn.po
i18n/nl.po
i18n/nl_BE.po
i18n/pl.po
i18n/pt.po
i18n/pt_BR.po
i18n/ro.po
i18n/ru.po
i18n/sl.po
i18n/sv.po
i18n/tr.po
i18n/zh_CN.po
images/costs_analysis.jpeg
images/indicative_costs_analysis.jpeg
images/vehicles.jpeg
images/vehicles_contracts.jpeg
images/vehicles_fuel.jpeg
images/vehicles_odometer.jpeg
images/vehicles_services.jpeg
openerp_fleet.egg-info/PKG-INFO
openerp_fleet.egg-info/SOURCES.txt
openerp_fleet.egg-info/dependency_links.txt
openerp_fleet.egg-info/requires.txt
openerp_fleet.egg-info/top_level.txt
security/fleet_security.xml
security/ir.model.access.csv
static/src/img/icon.png